MANIFEST.in
README.md
baryssh
setup.py
barySSH.egg-info/PKG-INFO
barySSH.egg-info/SOURCES.txt
barySSH.egg-info/dependency_links.txt
barySSH.egg-info/requires.txt
barySSH.egg-info/top_level.txt
barylib/barylib.c
barylib/barylib.pyx