Metadata-Version: 1.1
Name: barySSH
Version: 0.3.3
Summary: Proxy which uses simple time-based XOR scheme to make heuristic detection of underlying transmission impossible.
Home-page: https://github.com/blaa/barySSH
Author: Tomasz Fortuna
Author-email: bla@thera.be
License: MIT
Keywords: ssh xor masking proxy tunnel
Platform: UNKNOWN
Classifier: Development Status :: 3 - Alpha
Classifier: Topic :: Utilities
Classifier: License :: OSI Approved :: MIT License
